odoorpc_toolbox/__init__.py
odoorpc_toolbox/_version.py
odoorpc_toolbox/base_helper.py
odoorpc_toolbox/introspection.py
odoorpc_toolbox/odoo_connection.py
odoorpc_toolbox-0.3.0.dist-info/licenses/LICENSE.txt
odoorpc_toolbox-0.3.0.dist-info/METADATA
odoorpc_toolbox-0.3.0.dist-info/WHEEL
odoorpc_toolbox-0.3.0.dist-info/top_level.txt
odoorpc_toolbox-0.3.0.dist-info/RECORD
