Metadata-Version: 2.4
Name: odoorpc-toolbox
Version: 0.3.0
Summary: Helper Functions for OdooRPC.
Home-page: https://github.com/equitania/odoorpc-toolbox
Author: Equitania Software GmbH
Author-email: info@equitania.de
Classifier: Programming Language :: Python :: 3
Classifier: License :: OSI Approved :: GNU Affero General Public License v3
Classifier: Operating System :: OS Independent
Requires-Python: >=3.8
License-File: LICENSE.txt
Requires-Dist: OdooRPC>=0.10.1
Requires-Dist: PyYaml>=5.4.1
Dynamic: author
Dynamic: author-email
Dynamic: classifier
Dynamic: description
Dynamic: description-content-type
Dynamic: home-page
Dynamic: license-file
Dynamic: requires-dist
Dynamic: requires-python
Dynamic: summary
